AUTHORS.rst
CONTRIBUTING.rst
HISTORY.rst
LICENSE
MANIFEST.in
README.rst
setup.cfg
setup.py
datavacuum/__init__.py
datavacuum/cli.py
datavacuum/datavacuum.py
datavacuum.egg-info/PKG-INFO
datavacuum.egg-info/SOURCES.txt
datavacuum.egg-info/dependency_links.txt
datavacuum.egg-info/entry_points.txt
datavacuum.egg-info/not-zip-safe
datavacuum.egg-info/requires.txt
datavacuum.egg-info/top_level.txt
docs/Makefile
docs/authors.rst
docs/conf.py
docs/contributing.rst
docs/history.rst
docs/index.rst
docs/installation.rst
docs/make.bat
docs/readme.rst
docs/usage.rst
tests/__init__.py
tests/test_datavacuum.py