Metadata-Version: 1.1
Name: datavacuum
Version: 0.1.0
Summary: CLI for data cleaning
Home-page: https://github.com/imohitawasthi/datavacuum
Author: Mohit Awasthi
Author-email: imohitawasthi@gmail.com
License: Apache Software License 2.0
Keywords: datavacuum
Platform: UNKNOWN
Classifier: Development Status :: 2 - Pre-Alpha
Classifier: Intended Audience :: Developers
Classifier: License :: OSI Approved :: Apache Software License
Classifier: Natural Language :: English
Classifier: Programming Language :: Python :: 2
Classifier: Programming Language :: Python :: 2.7
Classifier: Programming Language :: Python :: 3
Classifier: Programming Language :: Python :: 3.4
Classifier: Programming Language :: Python :: 3.5
Classifier: Programming Language :: Python :: 3.6
Classifier: Programming Language :: Python :: 3.7
